r3c0n/__init__.py
r3c0n/__main__.py
scripts/__init__.py
scripts/anubis.py
utils/__init__.py
utils/formatter.py
utils/viewer.py
r3c0n-1.0.7.dist-info/LICENSE
r3c0n-1.0.7.dist-info/METADATA
r3c0n-1.0.7.dist-info/WHEEL
r3c0n-1.0.7.dist-info/entry_points.txt
r3c0n-1.0.7.dist-info/top_level.txt
r3c0n-1.0.7.dist-info/RECORD
