Metadata-Version: 2.1
Name: r3c0n
Version: 1.0.7
Summary: A tool for performing reconnaissance on web targets in Python.
Home-page: https://github.com/markgacoka/r3c0n
Download-URL: https://github.com/markgacoka/r3c0n/releases
Author: Gacoka Mbui
Author-email: <markgacoka@gmail.com>
License: MIT
Keywords: cybersecurity,reconnaissance,scanning,automation
Platform: UNKNOWN
Classifier: Development Status :: 4 - Beta
Classifier: Intended Audience :: Developers
Classifier: License :: OSI Approved :: MIT License
Classifier: Operating System :: OS Independent
Classifier: Programming Language :: Python :: 3
Classifier: Topic :: Security
License-File: LICENSE
Requires-Dist: pathlib
Requires-Dist: yarl (==1.7.2)
